[
  {
    "name": null,
    "methods": [
      "HEAD",
      "GET"
    ],
    "paramNames": [],
    "path": "/api/v1/",
    "regexp": "/^\\/api\\/v1(?:\\/(?=$))?$/",
    "stack": [
      "wrappedController"
    ]
  },
  {
    "name": null,
    "methods": [
      "POST"
    ],
    "paramNames": [],
    "path": "/api/v1/auth/signup",
    "regexp": "/^\\/api\\/v1\\/auth\\/signup(?:\\/(?=$))?$/",
    "stack": [
      "wrappedController"
    ]
  },
  {
    "name": null,
    "methods": [
      "POST"
    ],
    "paramNames": [],
    "path": "/api/v1/auth/login",
    "regexp": "/^\\/api\\/v1\\/auth\\/login(?:\\/(?=$))?$/",
    "stack": [
      "wrappedController"
    ]
  },
  {
    "name": null,
    "methods": [
      "HEAD",
      "GET"
    ],
    "paramNames": [],
    "path": "/api/v1/auth/me",
    "regexp": "/^\\/api\\/v1\\/auth\\/me(?:\\/(?=$))?$/",
    "stack": [
      "anonymous",
      "wrappedController"
    ]
  },
  {
    "name": null,
    "methods": [
      "HEAD",
      "GET"
    ],
    "paramNames": [],
    "path": "/api/v1/users",
    "regexp": "/^\\/api\\/v1\\/users(?:\\/(?=$))?$/",
    "stack": [
      "wrappedController"
    ]
  },
  {
    "name": null,
    "methods": [
      "HEAD",
      "GET"
    ],
    "paramNames": [],
    "path": "/api/v1/user/subscriptions",
    "regexp": "/^\\/api\\/v1\\/user\\/subscriptions(?:\\/(?=$))?$/",
    "stack": [
      "wrappedController"
    ]
  },
  {
    "name": null,
    "methods": [
      "POST"
    ],
    "paramNames": [],
    "path": "/api/v1/user/subscriptions",
    "regexp": "/^\\/api\\/v1\\/user\\/subscriptions(?:\\/(?=$))?$/",
    "stack": [
      "wrappedController"
    ]
  },
  {
    "name": null,
    "methods": [
      "DELETE"
    ],
    "paramNames": [],
    "path": "/api/v1/user/subscriptions",
    "regexp": "/^\\/api\\/v1\\/user\\/subscriptions(?:\\/(?=$))?$/",
    "stack": [
      "wrappedController"
    ]
  },
  {
    "name": null,
    "methods": [
      "HEAD",
      "GET"
    ],
    "paramNames": [],
    "path": "/api/v1/videos",
    "regexp": "/^\\/api\\/v1\\/videos(?:\\/(?=$))?$/",
    "stack": [
      "wrappedController"
    ]
  },
  {
    "name": null,
    "methods": [
      "POST"
    ],
    "paramNames": [],
    "path": "/api/v1/videos",
    "regexp": "/^\\/api\\/v1\\/videos(?:\\/(?=$))?$/",
    "stack": [
      "anonymous",
      "wrappedController"
    ]
  },
  {
    "name": null,
    "methods": [
      "HEAD",
      "GET"
    ],
    "paramNames": [
      {
        "name": "id",
        "prefix": "/",
        "delimiter": "/",
        "optional": false,
        "repeat": false,
        "partial": false,
        "asterisk": false,
        "pattern": "[^\\/]+?"
      }
    ],
    "path": "/api/v1/videos/:id",
    "regexp": "/^\\/api\\/v1\\/videos\\/((?:[^\\/]+?))(?:\\/(?=$))?$/",
    "stack": [
      "wrappedController"
    ]
  },
  {
    "name": null,
    "methods": [
      "POST"
    ],
    "paramNames": [
      {
        "name": "videoId",
        "prefix": "/",
        "delimiter": "/",
        "optional": false,
        "repeat": false,
        "partial": false,
        "asterisk": false,
        "pattern": "[^\\/]+?"
      }
    ],
    "path": "/api/v1/videos/:videoId/likes",
    "regexp": "/^\\/api\\/v1\\/videos\\/((?:[^\\/]+?))\\/likes(?:\\/(?=$))?$/",
    "stack": [
      "anonymous",
      "wrappedController"
    ]
  },
  {
    "name": null,
    "methods": [
      "HEAD",
      "GET"
    ],
    "paramNames": [
      {
        "name": "action",
        "prefix": "/",
        "delimiter": "/",
        "optional": false,
        "repeat": false,
        "partial": false,
        "asterisk": false,
        "pattern": "[^\\/]+?"
      }
    ],
    "path": "/api/v1/api/v1/vod/:action",
    "regexp": "/^\\/api\\/v1\\/api\\/v1\\/vod\\/((?:[^\\/]+?))(?:\\/(?=$))?$/",
    "stack": [
      "wrappedController"
    ]
  }
]